dify_knowledge_pipeline/__init__.py
dify_knowledge_pipeline/client.py
dify_knowledge_pipeline/errors.py
dify_knowledge_pipeline/fire_drop.py
dify_knowledge_pipeline/models.py
dify_knowledge_pipeline/pipeline.py
dify_knowledge_pipeline-0.1.7.dist-info/LICENSE
dify_knowledge_pipeline-0.1.7.dist-info/METADATA
dify_knowledge_pipeline-0.1.7.dist-info/WHEEL
dify_knowledge_pipeline-0.1.7.dist-info/RECORD
